pycpdflib/__init__.py
pycpdflib/pycpdflib.py
pycpdflib-2.4.dist-info/LICENSE
pycpdflib-2.4.dist-info/METADATA
pycpdflib-2.4.dist-info/WHEEL
pycpdflib-2.4.dist-info/top_level.txt
pycpdflib-2.4.dist-info/RECORD
