Metadata-Version: 2.1
Name: pycpdflib
Version: 2.4
Summary: Python interface to Coherent PDF Tools
Home-page: https://coherentpdf.com/
Author: Coherent Graphics Ltd
Author-email: contact@coherentgraphics.co.uk
License: UNKNOWN
Project-URL: Bug Tracker, https://github.com/coherentgraphics/python-libcpdf/issues
Platform: UNKNOWN
Classifier: Programming Language :: Python :: 3
Classifier: License :: OSI Approved :: BSD License
Classifier: Operating System :: OS Independent
Requires-Python: >=3.8
License-File: LICENSE
